[
    {
        "type": "sourcecred/cli/scores",
        "version": "0.2.0"
    },
    {
        "intervals": [
            {
                "endTimeMs": 1584835200000,
                "startTimeMs": 1584230400000
            },
            {
                "endTimeMs": 1585440000000,
                "startTimeMs": 1584835200000
            },
            {
                "endTimeMs": 1586044800000,
                "startTimeMs": 1585440000000
            },
            {
                "endTimeMs": 1586649600000,
                "startTimeMs": 1586044800000
            }
        ],
        "users": [
            {
                "address": [
                    "sourcecred",
                    "discord",
                    "MEMBER",
                    "user",
                    "623941679069790209"
                ],
                "intervalCred": [
                    1.6332075855672104,
                    4.683487120727221,
                    4.352208192146443,
                    2.153288055832123
                ],
                "totalCred": 12.822190954272996
            },
            {
                "address": [
                    "sourcecred",
                    "discord",
                    "MEMBER",
                    "user",
                    "194817764236460034"
                ],
                "intervalCred": [
                    0.5321758145498382,
                    1.364186276569159,
                    3.806611779710868,
                    2.0059924167748404
                ],
                "totalCred": 7.708966287604706
            },
            {
                "address": [
                    "sourcecred",
                    "discord",
                    "MEMBER",
                    "user",
                    "690630857677078589"
                ],
                "intervalCred": [
                    0,
                    3.7021205822323884,
                    1.1565324062240134,
                    0.5784466441047642
                ],
                "totalCred": 5.437099632561166
            },
            {
                "address": [
                    "sourcecred",
                    "discord",
                    "MEMBER",
                    "user",
                    "594521360047538191"
                ],
                "intervalCred": [
                    0.014943384299983061,
                    1.6311327097528288,
                    1.5161050029616356,
                    1.8170822434087008
                ],
                "totalCred": 4.979263340423149
            },
            {
                "address": [
                    "sourcecred",
                    "discord",
                    "MEMBER",
                    "user",
                    "695420777771565083"
                ],
                "intervalCred": [
                    0,
                    0.023486663790282712,
                    1.8698075401154302,
                    2.5783514648840518
                ],
                "totalCred": 4.4716456687897645
            },
            {
                "address": [
                    "sourcecred",
                    "discord",
                    "MEMBER",
                    "user",
                    "657069807505637397"
                ],
                "intervalCred": [
                    1.1451836993647284,
                    1.545192806078598,
                    0.8737637825843623,
                    0.42825475360499055
                ],
                "totalCred": 3.9923950416326797
            },
            {
                "address": [
                    "sourcecred",
                    "discord",
                    "MEMBER",
                    "user",
                    "694625887005573261"
                ],
                "intervalCred": [
                    0,
                    0,
                    2.5736529529619854,
                    1.1680450601401988
                ],
                "totalCred": 3.741698013102184
            },
            {
                "address": [
                    "sourcecred",
                    "discord",
                    "MEMBER",
                    "user",
                    "426387669677899779"
                ],
                "intervalCred": [
                    0.022200144085164037,
                    1.257704622015142,
                    1.4501630750324048,
                    0.7294060677108444
                ],
                "totalCred": 3.4594739088435555
            },
            {
                "address": [
                    "sourcecred",
                    "discord",
                    "MEMBER",
                    "user",
                    "690191777096925257"
                ],
                "intervalCred": [
                    0,
                    0,
                    2.2858630342359376,
                    1.1648876021318904
                ],
                "totalCred": 3.450750636367828
            },
            {
                "address": [
                    "sourcecred",
                    "discord",
                    "MEMBER",
                    "user",
                    "265974270889426955"
                ],
                "intervalCred": [
                    0.7441444679287822,
                    1.6458437697459871,
                    0.6767647384066104,
                    0.334398512117959
                ],
                "totalCred": 3.4011514881993388
            },
            {
                "address": [
                    "sourcecred",
                    "discord",
                    "MEMBER",
                    "user",
                    "291388682710024192"
                ],
                "intervalCred": [
                    0,
                    0.3614247438229272,
                    1.9920155928668701,
                    0.9832204183322679
                ],
                "totalCred": 3.3366607550220655
            },
            {
                "address": [
                    "sourcecred",
                    "discord",
                    "MEMBER",
                    "user",
                    "690894073309036565"
                ],
                "intervalCred": [
                    0.2621936748594061,
                    1.1125424929649819,
                    1.300802583628786,
                    0.6280951452281297
                ],
                "totalCred": 3.3036338966813035
            },
            {
                "address": [
                    "sourcecred",
                    "discord",
                    "MEMBER",
                    "user",
                    "440281764204642314"
                ],
                "intervalCred": [
                    0,
                    0.6501082932100339,
                    1.2350523670573461,
                    0.802258918089859
                ],
                "totalCred": 2.687419578357239
            },
            {
                "address": [
                    "sourcecred",
                    "discord",
                    "MEMBER",
                    "user",
                    "354004199555465218"
                ],
                "intervalCred": [
                    0,
                    0.04239306633499101,
                    1.6837449980604449,
                    0.954132136732924
                ],
                "totalCred": 2.68027020112836
            },
            {
                "address": [
                    "sourcecred",
                    "discord",
                    "MEMBER",
                    "user",
                    "560218690088337429"
                ],
                "intervalCred": [
                    0,
                    0,
                    1.5087145354955827,
                    0.6246528374121603
                ],
                "totalCred": 2.1333673729077427
            },
            {
                "address": [
                    "sourcecred",
                    "discord",
                    "MEMBER",
                    "user",
                    "695680642821652480"
                ],
                "intervalCred": [
                    0,
                    0,
                    1.3647653767244496,
                    0.6764971923092367
                ],
                "totalCred": 2.0412625690336865
            },
            {
                "address": [
                    "sourcecred",
                    "discord",
                    "MEMBER",
                    "user",
                    "648950940140830740"
                ],
                "intervalCred": [
                    0,
                    1.0898294422090091,
                    0.5980353341399783,
                    0.3179615326686134
                ],
                "totalCred": 2.0058263090176007
            },
            {
                "address": [
                    "sourcecred",
                    "discord",
                    "MEMBER",
                    "user",
                    "695930850415607859"
                ],
                "intervalCred": [
                    0,
                    0,
                    1.1564210201377563,
                    0.6287578592311182
                ],
                "totalCred": 1.7851788793688743
            },
            {
                "address": [
                    "sourcecred",
                    "discord",
                    "MEMBER",
                    "user",
                    "490427240908324865"
                ],
                "intervalCred": [
                    0,
                    0,
                    1.1441553251603207,
                    0.5674687097813843
                ],
                "totalCred": 1.7116240349417051
            },
            {
                "address": [
                    "sourcecred",
                    "discord",
                    "MEMBER",
                    "user",
                    "360481131029856256"
                ],
                "intervalCred": [
                    0,
                    0.07435659865216691,
                    1.05836859222041,
                    0.5235440576463879
                ],
                "totalCred": 1.6562692485189647
            },
            {
                "address": [
                    "sourcecred",
                    "discord",
                    "MEMBER",
                    "user",
                    "381975610005782528"
                ],
                "intervalCred": [
                    0,
                    0,
                    1.0557178664496214,
                    0.5217510678173449
                ],
                "totalCred": 1.5774689342669663
            },
            {
                "address": [
                    "sourcecred",
                    "discord",
                    "MEMBER",
                    "user",
                    "208710861882130432"
                ],
                "intervalCred": [
                    0,
                    0.9911725617636218,
                    0.3816920973342499,
                    0.18897116570171626
                ],
                "totalCred": 1.561835824799588
            },
            {
                "address": [
                    "sourcecred",
                    "discord",
                    "MEMBER",
                    "user",
                    "692710590749212727"
                ],
                "intervalCred": [
                    0,
                    0,
                    0.8992063130736079,
                    0.44400691572174583
                ],
                "totalCred": 1.3432132287953538
            },
            {
                "address": [
                    "sourcecred",
                    "discord",
                    "MEMBER",
                    "user",
                    "695003567181791372"
                ],
                "intervalCred": [
                    0,
                    0,
                    0.7918950402578878,
                    0.3917762524298273
                ],
                "totalCred": 1.183671292687715
            },
            {
                "address": [
                    "sourcecred",
                    "discord",
                    "MEMBER",
                    "user",
                    "695594354513018890"
                ],
                "intervalCred": [
                    0,
                    0,
                    0.7217554026401278,
                    0.357068436515658
                ],
                "totalCred": 1.0788238391557858
            },
            {
                "address": [
                    "sourcecred",
                    "discord",
                    "MEMBER",
                    "user",
                    "95626928853098496"
                ],
                "intervalCred": [
                    0,
                    0.6088827046078978,
                    0.2805631305604787,
                    0.13881534591705033
                ],
                "totalCred": 1.0282611810854267
            },
            {
                "address": [
                    "sourcecred",
                    "discord",
                    "MEMBER",
                    "user",
                    "440810369402011649"
                ],
                "intervalCred": [
                    0,
                    0.6157880868207716,
                    0.24656958659388267,
                    0.12194188351093768
                ],
                "totalCred": 0.984299556925592
            },
            {
                "address": [
                    "sourcecred",
                    "discord",
                    "MEMBER",
                    "user",
                    "258654796079300610"
                ],
                "intervalCred": [
                    0,
                    0,
                    0.3120160084942802,
                    0.6714574106467607
                ],
                "totalCred": 0.9834734191410408
            },
            {
                "address": [
                    "sourcecred",
                    "discord",
                    "MEMBER",
                    "user",
                    "496233529894764545"
                ],
                "intervalCred": [
                    0,
                    0,
                    0,
                    0.9457162333536101
                ],
                "totalCred": 0.9457162333536101
            },
            {
                "address": [
                    "sourcecred",
                    "discord",
                    "MEMBER",
                    "user",
                    "686154009542656012"
                ],
                "intervalCred": [
                    0,
                    0.13680589846379695,
                    0.45657544854130994,
                    0.32255695174334464
                ],
                "totalCred": 0.9159382987484516
            },
            {
                "address": [
                    "sourcecred",
                    "discord",
                    "MEMBER",
                    "user",
                    "395673197615513600"
                ],
                "intervalCred": [
                    0,
                    0,
                    0.6202502768297921,
                    0.28919056979400953
                ],
                "totalCred": 0.9094408466238015
            },
            {
                "address": [
                    "sourcecred",
                    "discord",
                    "MEMBER",
                    "user",
                    "593783772516974627"
                ],
                "intervalCred": [
                    0,
                    0,
                    0.5578924882098807,
                    0.3014101020240011
                ],
                "totalCred": 0.8593025902338818
            },
            {
                "address": [
                    "sourcecred",
                    "discord",
                    "MEMBER",
                    "user",
                    "322148006352912385"
                ],
                "intervalCred": [
                    0,
                    0,
                    0.5664458443219508,
                    0.28401036622949405
                ],
                "totalCred": 0.8504562105514448
            },
            {
                "address": [
                    "sourcecred",
                    "discord",
                    "MEMBER",
                    "user",
                    "234000238262747138"
                ],
                "intervalCred": [
                    0,
                    0.47207834542187477,
                    0.2332715933186191,
                    0.11549202349132172
                ],
                "totalCred": 0.8208419622318156
            },
            {
                "address": [
                    "sourcecred",
                    "discord",
                    "MEMBER",
                    "user",
                    "306756239604318208"
                ],
                "intervalCred": [
                    0,
                    0.010289911984922571,
                    0.37164334064216903,
                    0.4227133172923991
                ],
                "totalCred": 0.8046465699194907
            },
            {
                "address": [
                    "sourcecred",
                    "discord",
                    "MEMBER",
                    "user",
                    "695903307952160768"
                ],
                "intervalCred": [
                    0,
                    0,
                    0.5381856596693959,
                    0.2660836732007152
                ],
                "totalCred": 0.8042693328701112
            },
            {
                "address": [
                    "sourcecred",
                    "discord",
                    "MEMBER",
                    "user",
                    "228483264409632768"
                ],
                "intervalCred": [
                    0,
                    0,
                    0.47171207014019506,
                    0.32895024452974103
                ],
                "totalCred": 0.8006623146699361
            },
            {
                "address": [
                    "sourcecred",
                    "discord",
                    "MEMBER",
                    "user",
                    "290101267454361601"
                ],
                "intervalCred": [
                    0,
                    0,
                    0.5359353192830854,
                    0.2626240947654498
                ],
                "totalCred": 0.7985594140485351
            },
            {
                "address": [
                    "sourcecred",
                    "discord",
                    "MEMBER",
                    "user",
                    "600341352433188867"
                ],
                "intervalCred": [
                    0,
                    0,
                    0.24335675786604305,
                    0.540442178747646
                ],
                "totalCred": 0.783798936613689
            },
            {
                "address": [
                    "sourcecred",
                    "discord",
                    "MEMBER",
                    "user",
                    "421133066451288075"
                ],
                "intervalCred": [
                    0,
                    0,
                    0.5196894479915902,
                    0.2571599595320314
                ],
                "totalCred": 0.7768494075236216
            },
            {
                "address": [
                    "sourcecred",
                    "discord",
                    "MEMBER",
                    "user",
                    "694924073561489481"
                ],
                "intervalCred": [
                    0,
                    0,
                    0.47937725470180953,
                    0.23666425327859905
                ],
                "totalCred": 0.7160415079804086
            },
            {
                "address": [
                    "sourcecred",
                    "discord",
                    "MEMBER",
                    "user",
                    "693563704507367555"
                ],
                "intervalCred": [
                    0,
                    0,
                    0.4749012755191216,
                    0.2359650770583923
                ],
                "totalCred": 0.7108663525775138
            },
            {
                "address": [
                    "sourcecred",
                    "discord",
                    "MEMBER",
                    "user",
                    "694559706198310913"
                ],
                "intervalCred": [
                    0.017553515199083655,
                    0.00909712314595805,
                    0.1493878283766239,
                    0.5339491818511819
                ],
                "totalCred": 0.7099876485728475
            },
            {
                "address": [
                    "sourcecred",
                    "discord",
                    "MEMBER",
                    "user",
                    "606579279861514240"
                ],
                "intervalCred": [
                    0,
                    0.018465405348836592,
                    0.43756593586325554,
                    0.22208390937800912
                ],
                "totalCred": 0.6781152505901012
            },
            {
                "address": [
                    "sourcecred",
                    "discord",
                    "MEMBER",
                    "user",
                    "250086586450968576"
                ],
                "intervalCred": [
                    0,
                    0.032897769350933026,
                    0.27804817212492716,
                    0.1372869525106385
                ],
                "totalCred": 0.4482328939864987
            },
            {
                "address": [
                    "sourcecred",
                    "discord",
                    "MEMBER",
                    "user",
                    "693448785967185980"
                ],
                "intervalCred": [
                    0,
                    0.022211247230145857,
                    0.2704596373487227,
                    0.1277272515854402
                ],
                "totalCred": 0.42039813616430877
            },
            {
                "address": [
                    "sourcecred",
                    "discord",
                    "MEMBER",
                    "user",
                    "672588809787146240"
                ],
                "intervalCred": [
                    0,
                    0.013556267018865167,
                    0.2294643395557504,
                    0.11348889575662727
                ],
                "totalCred": 0.35650950233124284
            },
            {
                "address": [
                    "sourcecred",
                    "discord",
                    "MEMBER",
                    "user",
                    "401023530109632513"
                ],
                "intervalCred": [
                    0,
                    0,
                    0.24252810046541937,
                    0.10710925353862782
                ],
                "totalCred": 0.34963735400404716
            },
            {
                "address": [
                    "sourcecred",
                    "discord",
                    "MEMBER",
                    "user",
                    "418322747827945473"
                ],
                "intervalCred": [
                    0,
                    0,
                    0.17660507182226504,
                    0.17206827992107995
                ],
                "totalCred": 0.348673351743345
            },
            {
                "address": [
                    "sourcecred",
                    "discord",
                    "MEMBER",
                    "user",
                    "403334649650216962"
                ],
                "intervalCred": [
                    0.04694550741163099,
                    0.06560306381867025,
                    0.13379340679497864,
                    0.06576310396832082
                ],
                "totalCred": 0.3121050819936007
            },
            {
                "address": [
                    "sourcecred",
                    "discord",
                    "MEMBER",
                    "user",
                    "693122956955615344"
                ],
                "intervalCred": [
                    0,
                    0,
                    0.07386696280562864,
                    0.10895480004885116
                ],
                "totalCred": 0.18282176285447982
            },
            {
                "address": [
                    "sourcecred",
                    "discord",
                    "MEMBER",
                    "user",
                    "357515308480856064"
                ],
                "intervalCred": [
                    0,
                    0.023486663790282712,
                    0.08485671570841193,
                    0.04200317663080456
                ],
                "totalCred": 0.15034655612949918
            },
            {
                "address": [
                    "sourcecred",
                    "discord",
                    "MEMBER",
                    "user",
                    "692951296210108456"
                ],
                "intervalCred": [
                    0,
                    0.02034555223782726,
                    0.08172314831857871,
                    0.04049320883232094
                ],
                "totalCred": 0.14256190938872693
            },
            {
                "address": [
                    "sourcecred",
                    "discord",
                    "MEMBER",
                    "user",
                    "420341518948237331"
                ],
                "intervalCred": [
                    0,
                    0.07435659865216691,
                    0.043017467457616344,
                    0.02169084489901605
                ],
                "totalCred": 0.1390649110087993
            },
            {
                "address": [
                    "sourcecred",
                    "discord",
                    "MEMBER",
                    "user",
                    "693089152870383626"
                ],
                "intervalCred": [
                    0,
                    0.019397347371436325,
                    0.025550911709892845,
                    0.0879156560897563
                ],
                "totalCred": 0.13286391517108548
            },
            {
                "address": [
                    "sourcecred",
                    "discord",
                    "MEMBER",
                    "user",
                    "690660615802585149"
                ],
                "intervalCred": [
                    0,
                    0.052930582195703194,
                    0.05283373168160151,
                    0.02608663708594058
                ],
                "totalCred": 0.13185095096324528
            },
            {
                "address": [
                    "sourcecred",
                    "discord",
                    "MEMBER",
                    "user",
                    "420651712488144898"
                ],
                "intervalCred": [
                    0,
                    0.023486663790282712,
                    0.058337543986847776,
                    0.02823309065393219
                ],
                "totalCred": 0.11005729843106267
            },
            {
                "address": [
                    "sourcecred",
                    "discord",
                    "MEMBER",
                    "user",
                    "376847970278178829"
                ],
                "intervalCred": [
                    0,
                    0.04206336639675647,
                    0.037803009988179495,
                    0.01868174269996569
                ],
                "totalCred": 0.09854811908490166
            },
            {
                "address": [
                    "sourcecred",
                    "discord",
                    "MEMBER",
                    "user",
                    "418498780476735490"
                ],
                "intervalCred": [
                    0,
                    0,
                    0.06255416942318388,
                    0.031254809986646294
                ],
                "totalCred": 0.09380897940983018
            },
            {
                "address": [
                    "sourcecred",
                    "discord",
                    "MEMBER",
                    "user",
                    "449703950656995328"
                ],
                "intervalCred": [
                    0,
                    0,
                    0.05302135927028059,
                    0.026427218000333968
                ],
                "totalCred": 0.07944857727061455
            },
            {
                "address": [
                    "sourcecred",
                    "discord",
                    "MEMBER",
                    "user",
                    "693562742161801218"
                ],
                "intervalCred": [
                    0,
                    0.05122011788792706,
                    0.01882584488556538,
                    0.009282065615234212
                ],
                "totalCred": 0.07932802838872666
            },
            {
                "address": [
                    "sourcecred",
                    "discord",
                    "MEMBER",
                    "user",
                    "639473326024163338"
                ],
                "intervalCred": [
                    0,
                    0,
                    0.05285663692904035,
                    0.026126734972312503
                ],
                "totalCred": 0.07898337190135285
            },
            {
                "address": [
                    "sourcecred",
                    "discord",
                    "MEMBER",
                    "user",
                    "559343771565948969"
                ],
                "intervalCred": [
                    0,
                    0,
                    0,
                    0.07349272510377122
                ],
                "totalCred": 0.07349272510377122
            },
            {
                "address": [
                    "sourcecred",
                    "discord",
                    "MEMBER",
                    "user",
                    "661948172029001733"
                ],
                "intervalCred": [
                    0,
                    0.03151048788523804,
                    0.02664994602268964,
                    0.013143804613322707
                ],
                "totalCred": 0.07130423852125038
            },
            {
                "address": [
                    "sourcecred",
                    "discord",
                    "MEMBER",
                    "user",
                    "618615769713868812"
                ],
                "intervalCred": [
                    0.022200144085164037,
                    0.027637253637577016,
                    0.006753720346339973,
                    0.0034760070717601162
                ],
                "totalCred": 0.06006712514084114
            },
            {
                "address": [
                    "sourcecred",
                    "discord",
                    "MEMBER",
                    "user",
                    "651472034093727745"
                ],
                "intervalCred": [
                    0.022200144085164037,
                    0.027637253637577016,
                    0.006753720346339973,
                    0.0034760070717601162
                ],
                "totalCred": 0.06006712514084114
            },
            {
                "address": [
                    "sourcecred",
                    "discord",
                    "MEMBER",
                    "user",
                    "690325603382984729"
                ],
                "intervalCred": [
                    0.022200144085164037,
                    0.027637253637577016,
                    0.006753720346339973,
                    0.0034760070717601162
                ],
                "totalCred": 0.06006712514084114
            },
            {
                "address": [
                    "sourcecred",
                    "discord",
                    "MEMBER",
                    "user",
                    "696453870230044672"
                ],
                "intervalCred": [
                    0,
                    0,
                    0,
                    0.058721876465339544
                ],
                "totalCred": 0.058721876465339544
            },
            {
                "address": [
                    "sourcecred",
                    "discord",
                    "MEMBER",
                    "user",
                    "678512620143378432"
                ],
                "intervalCred": [
                    0,
                    0,
                    0.009050767256175579,
                    0.0474170257406993
                ],
                "totalCred": 0.05646779299687488
            },
            {
                "address": [
                    "sourcecred",
                    "discord",
                    "MEMBER",
                    "user",
                    "694807576470224918"
                ],
                "intervalCred": [
                    0,
                    0.023486663790282712,
                    0.017612073279081503,
                    0.008698613529239138
                ],
                "totalCred": 0.04979735059860336
            },
            {
                "address": [
                    "sourcecred",
                    "discord",
                    "MEMBER",
                    "user",
                    "690593828696227840"
                ],
                "intervalCred": [
                    0.014851774478681332,
                    0.02092447728650288,
                    0.008743284750414628,
                    0.004461489824364826
                ],
                "totalCred": 0.04898102633996367
            },
            {
                "address": [
                    "sourcecred",
                    "discord",
                    "MEMBER",
                    "user",
                    "341932084010680325"
                ],
                "intervalCred": [
                    0,
                    0,
                    0.03223945956669137,
                    0.01592254581990463
                ],
                "totalCred": 0.048162005386596
            },
            {
                "address": [
                    "sourcecred",
                    "discord",
                    "MEMBER",
                    "user",
                    "404473952912539658"
                ],
                "intervalCred": [
                    0,
                    0,
                    0.025321926391645752,
                    0.01659386508858098
                ],
                "totalCred": 0.04191579148022673
            },
            {
                "address": [
                    "sourcecred",
                    "discord",
                    "MEMBER",
                    "user",
                    "345674269658710016"
                ],
                "intervalCred": [
                    0,
                    0.023486663790282712,
                    0.011824137420778189,
                    0.00585513958936096
                ],
                "totalCred": 0.04116594080042186
            },
            {
                "address": [
                    "sourcecred",
                    "discord",
                    "MEMBER",
                    "user",
                    "693663745980760084"
                ],
                "intervalCred": [
                    0,
                    0.023486663790282712,
                    0.011824137420778189,
                    0.00585513958936096
                ],
                "totalCred": 0.04116594080042186
            },
            {
                "address": [
                    "sourcecred",
                    "discord",
                    "MEMBER",
                    "user",
                    "568978038008840212"
                ],
                "intervalCred": [
                    0,
                    0,
                    0.027397655752741484,
                    0.013722210090606497
                ],
                "totalCred": 0.04111986584334798
            },
            {
                "address": [
                    "sourcecred",
                    "discord",
                    "MEMBER",
                    "user",
                    "386780644480516099"
                ],
                "intervalCred": [
                    0,
                    0.019397347371436325,
                    0.009112903714830756,
                    0.011007339697450373
                ],
                "totalCred": 0.03951759078371746
            },
            {
                "address": [
                    "sourcecred",
                    "discord",
                    "MEMBER",
                    "user",
                    "695317717586149444"
                ],
                "intervalCred": [
                    0,
                    0,
                    0.023044394284732955,
                    0.01109846774594997
                ],
                "totalCred": 0.034142862030682924
            },
            {
                "address": [
                    "sourcecred",
                    "discord",
                    "MEMBER",
                    "user",
                    "552258892030017536"
                ],
                "intervalCred": [
                    0,
                    0,
                    0.02422431277711615,
                    0.00964030836550964
                ],
                "totalCred": 0.03386462114262579
            },
            {
                "address": [
                    "sourcecred",
                    "discord",
                    "MEMBER",
                    "user",
                    "694501595345584169"
                ],
                "intervalCred": [
                    0,
                    0,
                    0.02216678934793139,
                    0.011401253537560864
                ],
                "totalCred": 0.033568042885492255
            },
            {
                "address": [
                    "sourcecred",
                    "discord",
                    "MEMBER",
                    "user",
                    "513394497850179629"
                ],
                "intervalCred": [
                    0,
                    0.018923182084978615,
                    0.008936887063182164,
                    0.00441060656304703
                ],
                "totalCred": 0.03227067571120781
            },
            {
                "address": [
                    "sourcecred",
                    "discord",
                    "MEMBER",
                    "user",
                    "690570063865970698"
                ],
                "intervalCred": [
                    0,
                    0,
                    0.019975958892308233,
                    0.009976116036486519
                ],
                "totalCred": 0.02995207492879475
            },
            {
                "address": [
                    "sourcecred",
                    "discord",
                    "MEMBER",
                    "user",
                    "512547770008207362"
                ],
                "intervalCred": [
                    0,
                    0,
                    0,
                    0.02976154768251684
                ],
                "totalCred": 0.02976154768251684
            },
            {
                "address": [
                    "sourcecred",
                    "discord",
                    "MEMBER",
                    "user",
                    "534883744860078120"
                ],
                "intervalCred": [
                    0,
                    0,
                    0.022387460653883688,
                    0.006564358845916817
                ],
                "totalCred": 0.028951819499800503
            },
            {
                "address": [
                    "sourcecred",
                    "discord",
                    "MEMBER",
                    "user",
                    "387678799623356436"
                ],
                "intervalCred": [
                    0,
                    0,
                    0.019071881729433415,
                    0.009423119841384631
                ],
                "totalCred": 0.028495001570818045
            },
            {
                "address": [
                    "sourcecred",
                    "discord",
                    "MEMBER",
                    "user",
                    "574276064998719498"
                ],
                "intervalCred": [
                    0,
                    0,
                    0.019071881729433415,
                    0.009423119841384631
                ],
                "totalCred": 0.028495001570818045
            },
            {
                "address": [
                    "sourcecred",
                    "discord",
                    "MEMBER",
                    "user",
                    "693155474039636018"
                ],
                "intervalCred": [
                    0,
                    0,
                    0.016970556013268242,
                    0.008385299264246195
                ],
                "totalCred": 0.02535585527751444
            },
            {
                "address": [
                    "sourcecred",
                    "discord",
                    "MEMBER",
                    "user",
                    "694581757399400528"
                ],
                "intervalCred": [
                    0,
                    0,
                    0.0168371154586091,
                    0.008319314199098546
                ],
                "totalCred": 0.025156429657707646
            },
            {
                "address": [
                    "sourcecred",
                    "discord",
                    "MEMBER",
                    "user",
                    "649429012170670081"
                ],
                "intervalCred": [
                    0,
                    0.01792828768387397,
                    0.004269082345607026,
                    0.002140272426629132
                ],
                "totalCred": 0.02433764245611013
            },
            {
                "address": [
                    "sourcecred",
                    "discord",
                    "MEMBER",
                    "user",
                    "690848116961837116"
                ],
                "intervalCred": [
                    0,
                    0,
                    0.013555243667002212,
                    0.006693484662327352
                ],
                "totalCred": 0.020248728329329564
            },
            {
                "address": [
                    "sourcecred",
                    "discord",
                    "MEMBER",
                    "user",
                    "443020936455782410"
                ],
                "intervalCred": [
                    0,
                    0,
                    0.008446397677722622,
                    0.004191738946996953
                ],
                "totalCred": 0.012638136624719576
            },
            {
                "address": [
                    "sourcecred",
                    "discord",
                    "MEMBER",
                    "user",
                    "503671818037493760"
                ],
                "intervalCred": [
                    0,
                    0,
                    0.008446397677722622,
                    0.004191738946996953
                ],
                "totalCred": 0.012638136624719576
            },
            {
                "address": [
                    "sourcecred",
                    "discord",
                    "MEMBER",
                    "user",
                    "687002382131134481"
                ],
                "intervalCred": [
                    0,
                    0,
                    0.006672934741735832,
                    0.003308873722197427
                ],
                "totalCred": 0.009981808463933258
            },
            {
                "address": [
                    "sourcecred",
                    "discord",
                    "MEMBER",
                    "user",
                    "693680089883476009"
                ],
                "intervalCred": [
                    0,
                    0,
                    0.006672934741735832,
                    0.003308873722197427
                ],
                "totalCred": 0.009981808463933258
            },
            {
                "address": [
                    "sourcecred",
                    "discord",
                    "MEMBER",
                    "user",
                    "692367215621701695"
                ],
                "intervalCred": [
                    0,
                    0,
                    0.005365908339755561,
                    0.002756117164931675
                ],
                "totalCred": 0.008122025504687236
            },
            {
                "address": [
                    "sourcecred",
                    "discord",
                    "MEMBER",
                    "user",
                    "417016704447545356"
                ],
                "intervalCred": [
                    0,
                    0,
                    0.0035459634164571974,
                    0.0010496266480572879
                ],
                "totalCred": 0.004595590064514485
            }
        ]
    }
]
